kemas/__init__.py
kemas/cli.py
kemas/gui.py
kemas/icon.ico
kemas-1.2.1.dist-info/licenses/LICENSE
kemas-1.2.1.dist-info/METADATA
kemas-1.2.1.dist-info/WHEEL
kemas-1.2.1.dist-info/entry_points.txt
kemas-1.2.1.dist-info/top_level.txt
kemas-1.2.1.dist-info/RECORD
