Metadata-Version: 2.4
Name: kemas
Version: 1.2.1
Summary: Kemas Backend untuk mengkonversi aplikasi Python menjadi executable (.exe) dengan antarmuka GUI yang mudah digunakan
Home-page: https://github.com/royhtml
Author: Dwi Bakti N Dev
Author-email: dwibakti76@gmail.com
Project-URL: Profile, https://profiledwibaktindev.netlify.app/
Project-URL: ich.io, https://royhtml.itch.io/
Project-URL: Facebook, https://www.facebook.com/Royhtml
Project-URL: Webtoons, https://www.webtoons.com/id/canvas/mariadb-hari-senin/episode-4-coding-championship/viewer?title_no=1065164&episode_no=4
Classifier: Programming Language :: Python :: 3
Classifier: License :: OSI Approved :: MIT License
Classifier: Operating System :: OS Independent
Requires-Python: >=3.6
License-File: LICENSE
Requires-Dist: pillow>=8.0
Requires-Dist: pyinstaller>=4.0
Requires-Dist: pyqt5>=5.15
Dynamic: author
Dynamic: author-email
Dynamic: classifier
Dynamic: description
Dynamic: description-content-type
Dynamic: home-page
Dynamic: license-file
Dynamic: project-url
Dynamic: requires-dist
Dynamic: requires-python
Dynamic: summary
